ab_core/cache/__init__.py
ab_core/cache/codec.py
ab_core/cache/exceptions.py
ab_core/cache/namespace.py
ab_core/cache/session_context.py
ab_core/cache/caches/__init__.py
ab_core/cache/caches/base.py
ab_core/cache/caches/disk.py
ab_core/cache/caches/inmemory.py
ab_core/cache/caches/redis.py
ab_core/cache/caches/template.py
ab_core/cache/schema/__init__.py
ab_core/cache/schema/cache_type.py
ab_cache-0.1.6.dist-info/METADATA
ab_cache-0.1.6.dist-info/WHEEL
ab_cache-0.1.6.dist-info/licenses/LICENSE
ab_cache-0.1.6.dist-info/RECORD
